assemblyline_service_client/VERSION
assemblyline_service_client/__init__.py
assemblyline_service_client/task_handler.py
assemblyline_service_client-4.7.0.1.dist-info/licenses/LICENCE.md
assemblyline_service_client-4.7.0.1.dist-info/METADATA
assemblyline_service_client-4.7.0.1.dist-info/WHEEL
assemblyline_service_client-4.7.0.1.dist-info/top_level.txt
assemblyline_service_client-4.7.0.1.dist-info/RECORD
