Metadata-Version: 2.4
Name: assemblyline-service-client
Version: 4.7.0.1
Summary: Assemblyline 4 - Service client
Home-page: https://github.com/CybercentreCanada/assemblyline-service-client/
Author: CCCS Assemblyline development team
Author-email: assemblyline@cyber.gc.ca
License: MIT
Keywords: assemblyline automated malware analysis gc canada cse-cst cse cst cyber cccs
Classifier: Development Status :: 5 - Production/Stable
Classifier: Intended Audience :: Developers
Classifier: Topic :: Software Development :: Libraries
Classifier: License :: OSI Approved :: MIT License
Classifier: Programming Language :: Python :: 3.7
Classifier: Programming Language :: Python :: 3.8
Classifier: Programming Language :: Python :: 3.9
License-File: LICENCE.md
Requires-Dist: assemblyline
Requires-Dist: assemblyline-core
Requires-Dist: python-socketio
Provides-Extra: test
Requires-Dist: pytest; extra == "test"
Dynamic: author
Dynamic: author-email
Dynamic: classifier
Dynamic: description
Dynamic: description-content-type
Dynamic: home-page
Dynamic: keywords
Dynamic: license
Dynamic: license-file
Dynamic: provides-extra
Dynamic: requires-dist
Dynamic: summary
